logmiddleware/__init__.py
logmiddleware/middleware.py
logmiddleware-0.0.4.dist-info/METADATA
logmiddleware-0.0.4.dist-info/WHEEL
logmiddleware-0.0.4.dist-info/licenses/LICENSE.md
logmiddleware-0.0.4.dist-info/RECORD
