Metadata-Version: 2.1
Name: logmiddleware
Version: 0.0.4
Summary: Simplify the logging of incoming requests and outgoing responses.
Project-URL: Homepage, https://git.slc.ar/slococo/logmiddleware
Project-URL: Repository, https://git.slc.ar/slococo/logmiddleware
Author-email: Santiago Lo Coco <mail@slococo.com.ar>
License-Expression: MIT
License-File: LICENSE.md
Classifier: Intended Audience :: Developers
Classifier: Intended Audience :: Information Technology
Classifier: Intended Audience :: System Administrators
Classifier: License :: OSI Approved :: MIT License
Classifier: Operating System :: OS Independent
Classifier: Programming Language :: Python
Classifier: Programming Language :: Python :: 3
Classifier: Programming Language :: Python :: 3 :: Only
Classifier: Programming Language :: Python :: 3.8
Classifier: Programming Language :: Python :: 3.9
Classifier: Programming Language :: Python :: 3.10
Classifier: Programming Language :: Python :: 3.11
Classifier: Topic :: Internet
Classifier: Topic :: Software Development
Classifier: Topic :: Software Development :: Libraries
Classifier: Topic :: Software Development :: Libraries :: Python Modules
Classifier: Typing :: Typed
Requires-Python: >=3.8
Requires-Dist: fastapi>=0.103.2
Requires-Dist: python-json-logger>=2.0.7
